aws_ecr_migration/__init__.py
aws_ecr_migration/aws_credentials.py
aws_ecr_migration/ecr_pull.sh
aws_ecr_migration/ecr_push_container.sh
aws_ecr_migration/ecr_push_image.sh
aws_ecr_migration/manage.py
aws_ecr_migration-1.2.1.dist-info/LICENSE.txt
aws_ecr_migration-1.2.1.dist-info/METADATA
aws_ecr_migration-1.2.1.dist-info/WHEEL
aws_ecr_migration-1.2.1.dist-info/top_level.txt
aws_ecr_migration-1.2.1.dist-info/RECORD
