Metadata-Version: 2.1
Name: aws-ecr-migration
Version: 1.2.1
Summary: Management project which migrates docker images to/from ECR repositories.
Home-page: https://github.com/laimonassutkus/AwsEcrMigration
Author: Laimonas Sutkus
Author-email: laimonas@myhealthyapps.com
License: UNKNOWN
Keywords: AWS SDK ECR Docker Container Backup Restore Migration Infrastructure Cloud Lambda
Platform: UNKNOWN
Classifier: Programming Language :: Python :: 3
Classifier: Programming Language :: Python :: 3.5
Classifier: Programming Language :: Python :: 3.6
Classifier: Operating System :: POSIX :: Linux
Requires-Dist: boto3
Requires-Dist: botocore
Requires-Dist: awscli (<1.17.0,>=1.16.0)
